gpu_debugger/__init__.py
gpu_debugger/gpu.py
gpu_debugger-0.1.dist-info/AUTHORS.rst
gpu_debugger-0.1.dist-info/LICENSE.txt
gpu_debugger-0.1.dist-info/METADATA
gpu_debugger-0.1.dist-info/WHEEL
gpu_debugger-0.1.dist-info/top_level.txt
gpu_debugger-0.1.dist-info/RECORD
