Metadata-Version: 2.1
Name: gpu-debugger
Version: 0.1
Summary: Add a short description here!
Home-page: https://github.com/pyscaffold/pyscaffold/
Author: kula
Author-email: kulasama@foxmail.com
License: MIT
Project-URL: Documentation, https://pyscaffold.org/
Platform: any
Classifier: Development Status :: 4 - Beta
Classifier: Programming Language :: Python
Requires-Dist: nvidia-ml-py3
Provides-Extra: testing
Requires-Dist: pytest ; extra == 'testing'
Requires-Dist: pytest-cov ; extra == 'testing'
